piwars2026lib/__init__.py
piwars2026lib/drive_control.py
piwars2026lib/gpio_config.py
piwars2026lib/joystick_controller.py
piwars2026lib/motors.py
piwars2026lib-1.0.0.dist-info/licenses/LICENSE
piwars2026lib-1.0.0.dist-info/METADATA
piwars2026lib-1.0.0.dist-info/WHEEL
piwars2026lib-1.0.0.dist-info/top_level.txt
piwars2026lib-1.0.0.dist-info/RECORD
