Metadata-Version: 2.4
Name: piwars2026lib
Version: 1.0.0
Summary: A modular library system for robot control with motor drivers, joystick controllers, and GPIO management
Author-email: Your Name <your.email@example.com>
License: MIT
Project-URL: Homepage, https://github.com/yourusername/piwars2026lib
Project-URL: Documentation, https://github.com/yourusername/piwars2026lib#readme
Project-URL: Repository, https://github.com/yourusername/piwars2026lib
Project-URL: Issues, https://github.com/yourusername/piwars2026lib/issues
Keywords: raspberry-pi,gpio,motor-control,joystick,robotics,l298n
Classifier: Development Status :: 4 - Beta
Classifier: Intended Audience :: Developers
Classifier: License :: OSI Approved :: MIT License
Classifier: Programming Language :: Python :: 3
Classifier: Programming Language :: Python :: 3.7
Classifier: Programming Language :: Python :: 3.8
Classifier: Programming Language :: Python :: 3.9
Classifier: Programming Language :: Python :: 3.10
Classifier: Programming Language :: Python :: 3.11
Classifier: Topic :: System :: Hardware
Classifier: Topic :: Software Development :: Libraries :: Python Modules
Requires-Python: >=3.7
License-File: LICENSE
Requires-Dist: RPi.GPIO
Requires-Dist: pygame
Provides-Extra: dev
Requires-Dist: pytest>=7.0; extra == "dev"
Requires-Dist: black; extra == "dev"
Requires-Dist: flake8; extra == "dev"
Dynamic: license-file
